{"acRate": 86.45048375053618, "difficulty": "Easy", "freqBar": null, "frontendQuestionId": "1365", "isFavor": false, "paidOnly": false, "status": null, "title": "How Many Numbers Are Smaller Than the Current Number", "titleSlug": "how-many-numbers-are-smaller-than-the-current-number", "topicTags": [{"name": "Array", "id": "VG9waWNUYWdOb2RlOjU=", "slug": "array"}, {"name": "Hash Table", "id": "VG9waWNUYWdOb2RlOjY=", "slug": "hash-table"}, {"name": "Sorting", "id": "VG9waWNUYWdOb2RlOjYxMDQ5", "slug": "sorting"}, {"name": "Counting", "id": "VG9waWNUYWdOb2RlOjYxMDYy", "slug": "counting"}], "hasSolution": false, "hasVideoSolution": false}