{"acRate": 48.751467398873835, "difficulty": "Medium", "freqBar": null, "frontendQuestionId": "1034", "isFavor": false, "paidOnly": false, "status": null, "title": "Coloring A Border", "titleSlug": "coloring-a-border", "topicTags": [{"name": "Array", "id": "VG9waWNUYWdOb2RlOjU=", "slug": "array"}, {"name": "Depth-First Search", "id": "VG9waWNUYWdOb2RlOjIx", "slug": "depth-first-search"}, {"name": "Breadth-First Search", "id": "VG9waWNUYWdOb2RlOjIy", "slug": "breadth-first-search"}, {"name": "Matrix", "id": "VG9waWNUYWdOb2RlOjYxMDUz", "slug": "matrix"}], "hasSolution": false, "hasVideoSolution": false}