{"acRate": 43.243704784674144, "difficulty": "Medium", "freqBar": null, "frontendQuestionId": "1348", "isFavor": false, "paidOnly": false, "status": null, "title": "Tweet Counts Per Frequency", "titleSlug": "tweet-counts-per-frequency", "topicTags": [{"name": "Hash Table", "id": "VG9waWNUYWdOb2RlOjY=", "slug": "hash-table"}, {"name": "Binary Search", "id": "VG9waWNUYWdOb2RlOjEx", "slug": "binary-search"}, {"name": "Design", "id": "VG9waWNUYWdOb2RlOjI1", "slug": "design"}, {"name": "Sorting", "id": "VG9waWNUYWdOb2RlOjYxMDQ5", "slug": "sorting"}, {"name": "Ordered Set", "id": "VG9waWNUYWdOb2RlOjYxMDcw", "slug": "ordered-set"}], "hasSolution": false, "hasVideoSolution": false}