{"acRate": 63.010701511992586, "difficulty": "Medium", "freqBar": null, "frontendQuestionId": "714", "isFavor": false, "paidOnly": false, "status": null, "title": "Best Time to Buy and Sell Stock with Transaction Fee", "titleSlug": "best-time-to-buy-and-sell-stock-with-transaction-fee", "topicTags": [{"name": "Array", "id": "VG9waWNUYWdOb2RlOjU=", "slug": "array"}, {"name": "Dynamic Programming", "id": "VG9waWNUYWdOb2RlOjEz", "slug": "dynamic-programming"}, {"name": "Greedy", "id": "VG9waWNUYWdOb2RlOjE3", "slug": "greedy"}], "hasSolution": true, "hasVideoSolution": false}